{
  "b": "បង",
  "bab": "បាប",
  "bach": [
    "បាច់",
    "បាច"
  ],
  "backup": "ទុកបម្រុង",
  "baitong": "បៃតង",
  "baj": "បាច់",
  "bak": "បាក់",
  "ball": "បាល់",
  "ban": "បាន",
  "banhchi": "បញ្ជី",
  "banhchob": "បញ្ចប់",
  "banhjenh": "បញ្ចេញ",
  "banhjun": "បញ្ជូន",
  "banjeak": "បញ្ជាក់",
  "banteay": "បន្ទាយ",
  "bao": [
    "បាវ",
    "បៅ"
  ],
  "baok": "បោក",
  "baon": "ប្អូន",
  "bar": "បារ",
  "baramey": "បារមី",
  "barang": "បារាំង",
  "baras": "បារាស",
  "barates": "បរទេស",
  "baray": "បារាយណ៍",
  "barey": "បារី",
  "barom": "បារម្ភ",
  "bart": "បាទ",
  "bas": [
    "បាស់",
    "បាស"
  ],
  "basak": "បាសាក់",
  "bat": [
    "បាទ",
    "បាត់"
  ],
  "batbang": "បាត់បង់",
  "batbong": "បាត់បង់",
  "batokam": "បាតុកម្ម",
  "batokor": "បាតុករ",
  "batophut": "បាតុភូត",
  "battambang": "បាត់ដំបង",
  "bav": "បាវ",
  "bavajana": "បាវចនា",
  "bay": "បាយ",
  "bayon": "បាយ័ន",
  "baysey": "បាយសី",
  "baysra": "បាយស្រា",
  "bebot": "បែបបទ",
  "ber": "បើ",
  "bet": [
    "បិទ",
    "បិត"
  ],
  "bg": "បង",
  "bich": "ប៊ិច",
  "bik": "ប៊ិក",
  "bit": [
    "បិទ",
    "បិត"
  ],
  "bmc": "បន្ទាយមានជ័យ",
  "bok": "បុក",
  "bong": "បង",
  "bongouch": "បង្អួច",
  "bongrean": "បង្រៀន",
  "bongrien": "បង្រៀន",
  "bonman": "ប៉ុន្មាន",
  "bontae": "ប៉ុន្តែ",
  "bonthem": "បន្ថែម",
  "bontob": "បន្ទាប់",
  "bontort": "បន្ទាត់",
  "bontot": "បន្ទាត់",
  "borihan": "បរិហារ",
  "boros": "បុរស",
  "brak": "ប្រាក់",
  "bro": "ប្រូ",
  "brojum": "ប្រជុំ",
  "bros": "ប្រុស",
  "btb": "បាត់ដំបង",
  "bul": "បួល",
  "buol": "បួល",
  "but": [
    "តែ",
    "ប៉ុន្តែ"
  ]
}
